sentry_auth_chy/__init__.py
sentry_auth_chy/constants.py
sentry_auth_chy/provider.py
sentry_auth_chy/utils.py
sentry_auth_chy/views.py
sentry_auth_chy/templates/sentry_auth_chy/configure.html
sentry_auth_chy/templates/sentry_auth_google/configure.html
sentry_auth_chy-0.1.1.dist-info/LICENSE
sentry_auth_chy-0.1.1.dist-info/METADATA
sentry_auth_chy-0.1.1.dist-info/WHEEL
sentry_auth_chy-0.1.1.dist-info/entry_points.txt
sentry_auth_chy-0.1.1.dist-info/top_level.txt
sentry_auth_chy-0.1.1.dist-info/RECORD
